{
  "connection": "default",
  "collectionName": "",
  "info": {
    "name": "institution",
    "description": "Dados sobre a IES da qual fazem parte as divisões administrativas, acadêmicas e científicas sobre as quais trata o site."
  },
  "options": {
    "timestamps": true
  },
  "attributes": {
    "nome_extenso": {
      "required": true,
      "type": "string"
    },
    "sigla": {
      "required": true,
      "type": "string"
    },
    "categoria_administrativa": {
      "enum": [
        "nao_especificada",
        "publica_federal",
        "publica_estadual_ou_distrital",
        "publica_municipal",
        "privada_de_origem_publica_federal",
        "privada_de_origem_publica_estadual_ou_distrital",
        "privada_de_origem_publica_municipal",
        "privada_com_ou_sem_fins_lucrativos"
      ],
      "type": "enumeration",
      "required": true
    },
    "link_site_principal": {
      "required": true,
      "type": "string"
    },
    "logo": {
      "model": "logo"
    }
  }
}